persistent_dict-0.1.1.dist-info/DESCRIPTION.rst
persistent_dict-0.1.1.dist-info/METADATA
persistent_dict-0.1.1.dist-info/RECORD
persistent_dict-0.1.1.dist-info/WHEEL
persistent_dict-0.1.1.dist-info/metadata.json
persistent_dict-0.1.1.dist-info/top_level.txt
persistentdict/__init__.py
persistentdict/dict.py
