Metadata-Version: 2.0
Name: persistent-dict
Version: 0.1.1
Summary: A Python Dict which stores data in Redis.
Home-page: UNKNOWN
Author: Richard O'Dwyer
Author-email: richard@richard.do
License: MIT
Platform: UNKNOWN
Classifier: Intended Audience :: Developers
Classifier: Operating System :: OS Independent
Classifier: Programming Language :: Python
Classifier: Programming Language :: Python :: 2
Classifier: Programming Language :: Python :: 2.7
Classifier: Programming Language :: Python :: 3
Classifier: Programming Language :: Python :: 3.2
Classifier: Programming Language :: Python :: 3.4
Classifier: Programming Language :: Python :: 3.5
Classifier: Programming Language :: Python :: 3.6
